{
  "Version": "2012-10-17",
  "Statement": [
    {
      "Effect": "Allow",
      "Action": [
        "ec2:*",
        "ecs:*",
        "elasticloadbalancing:*",
        "autoscaling:*",
        "application-autoscaling:*",
        "rds:*",
        "elasticache:*",
        "logs:*",
        "iam:Get*",
        "iam:List*",
        "iam:CreateRole",
        "iam:DeleteRole",
        "iam:TagRole",
        "iam:UntagRole",
        "iam:PassRole",
        "iam:AttachRolePolicy",
        "iam:DetachRolePolicy",
        "iam:PutRolePolicy",
        "iam:DeleteRolePolicy",
        "cloudwatch:*",
        "events:*",
        "ecr:GetAuthorizationToken",
        "ecr:BatchCheckLayerAvailability",
        "ecr:GetDownloadUrlForLayer",
        "ecr:InitiateLayerUpload",
        "ecr:UploadLayerPart",
        "ecr:CompleteLayerUpload",
        "ecr:PutImage",
        "ecr:DescribeRepositories",
        "ecr:ListImages",
        "ecr:CreateRepository",
        "kms:DescribeKey",
        "kms:ListAliases",
        "kms:ListKeys",
        "s3:ListBucket",
        "s3:GetObject",
        "s3:PutObject",
        "s3:DeleteObject",
        "s3:GetBucketLocation",
        "s3:PutObjectAcl",
        "dynamodb:GetItem",
        "dynamodb:PutItem",
        "dynamodb:DeleteItem",
        "dynamodb:UpdateItem",
        "dynamodb:DescribeTable",
        "dynamodb:ListTables",
        "secretsmanager:GetSecretValue",
        "secretsmanager:DescribeSecret",
        "secretsmanager:PutSecretValue",
        "secretsmanager:ListSecrets",
        "ssm:GetParameter",
        "ssm:GetParameters",
        "ssm:DescribeParameters"
      ],
      "Resource": "*"
    }
  ]
}
